{
    "description": "Team1 hover gains v2 - trim values match Team1 geometry, pitch_rate kp scaled for actual Iyy (~8.7 slug*ft^2 from MAVRIK component model, NOT the suspect 0.45 from CAD).",
    "loop_rate_hz": 50,
    "mode": "hover",
    "flaps_value": 0.99,
    "trim": {
        "description": "Trim corrected for actual CG location (x=-0.129 ft from MAVRIK component model). Effective arms: tilt=+1.87 ft, vtol=-1.76 ft. Pitch balance requires T_aft slightly HIGHER than T_fwd (opposite of what nominal motor positions would suggest, because CG sits aft of origin).",
        "throttle_fwd": 0.39,
        "throttle_aft": 0.414,
        "aileron_deg": 0.0,
        "elevator_deg": 0.0,
        "rudder_deg": 0.0,
        "lift_balance_factor": 1.0,
        "lift_balance_note": "= sin(fwd_tilt_angle). At flaps=0.99 motors are ~89.1 deg from horizontal, sin(89.1)=0.9999, so 1.0 is correct.",
        "_arm_calc": "tilt arm = 1.74-(-0.129)=1.87 ft, vtol arm = -1.89-(-0.129)=-1.76 ft. T_fwd/T_aft = 1.76/1.87 = 0.941. With W=159.6 lbf: T_aft=41.1 lbf (=0.414 throttle), T_fwd=38.7 lbf (=0.390 throttle)."
    },
    "safety": {
        "max_throttle_step": 0.05,
        "max_surface_step_deg": 5.0,
        "ramp_in_seconds": 2.0,
        "warmup_seconds": 5.0
    },
    "altitude": {
        "tuning_note": "Bumped kp 0.3->0.5, kd 0.1->0.15 for faster altitude step response. Previous run showed ~15s to reach 8/10 ft — targeting ~8s.",
        "kp": 0.5,
        "ki": 0.05,
        "kd": 0.15,
        "output_min": -5.0,
        "output_max": 5.0,
        "integrator_max": 10.0
    },
    "climb_rate": {
        "tuning_note": "Bumped kp 0.02->0.04 for more aggressive collective response. ki stays the same to avoid steady-state drift.",
        "kp": 0.04,
        "ki": 0.005,
        "kd": 0.0,
        "output_min": -0.35,
        "output_max": 0.35,
        "integrator_max": 5.0
    },
    "roll_attitude": {
        "kp": 1.5,
        "ki": 0.0,
        "kd": 0.5,
        "output_min": -15.0,
        "output_max": 15.0
    },
    "roll_rate": {
        "tuning_note": "demo Ixx=195 slug*ft^2 with kp=0.006. Team1 Ixx printed by MAVRIK ~ check from new mass-properties output. Estimated ~8 slug*ft^2 -> kp ~ 0.006 * 8/195 = 0.00025. Use this as starting point.",
        "kp": 0.001,
        "ki": 0.0001,
        "kd": 0.0,
        "output_min": -0.15,
        "output_max": 0.15,
        "integrator_max": 3.0
    },
    "pitch_attitude": {
        "kp": 2.0,
        "ki": 0.5,
        "kd": 0.2,
        "output_min": -15.0,
        "output_max": 15.0,
        "integrator_max": 5.0
    },
    "pitch_rate": {
        "tuning_note": "Bumped from 0.00025 to 0.001 (4x). At 0.00025 saw 24deg pitch peak with oscillation period ~7s -- underdamped, too slow. 4x bump targets faster catch on initial transient. Halve if oscillates.",
        "kp": 0.001,
        "ki": 0.0001,
        "kd": 5e-05,
        "output_min": -0.1,
        "output_max": 0.1,
        "integrator_max": 3.0
    },
    "u_velocity": {
        "enabled": false,
        "kp": 0.05,
        "ki": 0.005,
        "kd": 0.0,
        "output_min": -2.0,
        "output_max": 2.0,
        "integrator_max": 5.0
    },
    "yaw_attitude": {
        "enabled": true,
        "kp": 0.3,
        "ki": 0.0,
        "kd": 0.05,
        "output_min": -10.0,
        "output_max": 10.0,
        "note": "Enabled for yaw test. Rudder authority is weak in hover so expect slow response. 15deg heading change test at t=100s."
    },
    "yaw_rate": {
        "tuning_note": "Output is now flaps differential (not rudder deg). ±0.03 max = ±2.7deg tilt asymmetry. kp=0.001 is conservative — at ~480 ft*lbf/unit_flaps_diff, this gives ~0.48 ft*lbf per deg/s rate error.",
        "kp": 0.001,
        "ki": 0.0002,
        "kd": 0.0,
        "output_min": -0.03,
        "output_max": 0.03,
        "integrator_max": 0.02
    },
    "setpoints": {
        "description": "Full test sequence: hover settle -> roll test -> alt step -> yaw test -> settle",
        "schedule": [
            {
                "time": 0.0,
                "phi_deg": 0.0,
                "theta_deg": 0.0,
                "alt_ft": 1000.0,
                "psi_deg": 0.0,
                "u_ft_s": 0.0,
                "_note": "Hover settle (warmup 5s + 25s steady)"
            },
            {
                "time": 30.0,
                "phi_deg": 0.0,
                "theta_deg": 0.0,
                "alt_ft": 1000.0,
                "u_ft_s": 0.0
            },
            {
                "time": 40.0,
                "phi_deg": 5.0,
                "theta_deg": 0.0,
                "alt_ft": 1000.0,
                "u_ft_s": 0.0,
                "_note": "Roll test: 5deg right"
            },
            {
                "time": 55.0,
                "phi_deg": 0.0,
                "theta_deg": 0.0,
                "alt_ft": 1000.0,
                "u_ft_s": 0.0,
                "_note": "Return to wings-level"
            },
            {
                "time": 70.0,
                "phi_deg": 0.0,
                "theta_deg": 0.0,
                "alt_ft": 1010.0,
                "u_ft_s": 0.0,
                "_note": "Altitude step: +10 ft"
            },
            {
                "time": 90.0,
                "phi_deg": 0.0,
                "theta_deg": 0.0,
                "alt_ft": 1000.0,
                "u_ft_s": 0.0,
                "_note": "Return to 1000 ft"
            },
            {
                "time": 100.0,
                "phi_deg": 0.0,
                "theta_deg": 0.0,
                "alt_ft": 1000.0,
                "psi_deg": 15.0,
                "u_ft_s": 0.0,
                "_note": "Yaw test: 15deg heading change"
            },
            {
                "time": 120.0,
                "phi_deg": 0.0,
                "theta_deg": 0.0,
                "alt_ft": 1000.0,
                "psi_deg": 0.0,
                "u_ft_s": 0.0,
                "_note": "Return to 0deg heading"
            },
            {
                "time": 140.0,
                "phi_deg": 0.0,
                "theta_deg": 0.0,
                "alt_ft": 1000.0,
                "psi_deg": 0.0,
                "u_ft_s": 0.0,
                "_note": "Final settle"
            }
        ]
    },
    "ports": {
        "state_receive": 5007,
        "control_send": 5006,
        "control_ip": "127.0.0.1"
    },
    "logging": {
        "filename": "pid_log.csv",
        "rate_hz": 30
    }
}